slurmbridge/__init__.py
slurmbridge/cliobject.py
slurmbridge/common.py
slurmbridge/objects.py
slurmbridge/sacctmgr.py
slurmbridge/scancel.py
slurmbridge/scontrol.py
slurmbridge-0.1.5.dist-info/WHEEL
slurmbridge-0.1.5.dist-info/METADATA
slurmbridge-0.1.5.dist-info/RECORD
